lgi.py
django_lgi-0.1.2.dist-info/LICENSE
django_lgi-0.1.2.dist-info/WHEEL
django_lgi-0.1.2.dist-info/METADATA
django_lgi-0.1.2.dist-info/RECORD
