Metadata-Version: 2.1
Name: django-lgi
Version: 0.1.2
Summary: Django Lambda Gateway Interface
Home-page: https://github.com/jwygoda/django-lgi
License: UNKNOWN
Author: Jarosław Wygoda
Author-email: jaroslaw@wygoda.me
Requires-Python: >=3.6
Classifier: License :: OSI Approved :: MIT License
Classifier: Development Status :: 3 - Alpha
Classifier: Programming Language :: Python :: 3.6
Classifier: Programming Language :: Python :: 3.7
Classifier: Programming Language :: Python :: 3.8
Classifier: Framework :: Django :: 3.0
Classifier: Framework :: Django :: 3.1
Requires-Dist: django>=3
Requires-Dist: black ; extra == "dev"
Requires-Dist: isort ; extra == "dev"
Requires-Dist: pre-commit ; extra == "dev"
Requires-Dist: tox ; extra == "test"
Provides-Extra: dev
Provides-Extra: test
